{
  "meta": {
    "make": "CHEVROLET",
    "generated_at": "2026-01-15T17:43:25.012763",
    "database": "mot_insights.db",
    "national_pass_rate": 71.51084606960882,
    "methodology_version": "2.1",
    "methodology_note": "Year-adjusted scoring: model comparisons use same-year national averages. Age-band comparisons use weighted national averages. Only vehicles with 11+ years of data are classified as 'proven' durability."
  },
  "overview": {
    "id": 74,
    "make": "CHEVROLET",
    "total_tests": 64975,
    "total_models": 729,
    "avg_pass_rate": 54.36,
    "weighted_pass_rate": 54.36,
    "best_model": "TRAX 2014",
    "best_model_pass_rate": 73.03,
    "worst_model": "LACETTI 2006",
    "worst_model_pass_rate": 40.22,
    "rank": 74
  },
  "competitors": [
    {
      "make": "TOYOTA",
      "avg_pass_rate": 73.97,
      "total_tests": 1606300,
      "rank": 31,
      "total_models": 4710
    },
    {
      "make": "VOLKSWAGEN",
      "avg_pass_rate": 72.15,
      "total_tests": 2967545,
      "rank": 43,
      "total_models": 3024
    },
    {
      "make": "NISSAN",
      "avg_pass_rate": 68.66,
      "total_tests": 1612552,
      "rank": 50,
      "total_models": 2554
    },
    {
      "make": "FORD",
      "avg_pass_rate": 68.46,
      "total_tests": 4432652,
      "rank": 51,
      "total_models": 4002
    },
    {
      "make": "VAUXHALL",
      "avg_pass_rate": 65.44,
      "total_tests": 3038498,
      "rank": 59,
      "total_models": 1856
    },
    {
      "make": "CHEVROLET",
      "avg_pass_rate": 54.36,
      "total_tests": 64975,
      "rank": 74,
      "total_models": 729
    }
  ],
  "summary": {
    "total_tests": 64975,
    "total_models": 729,
    "avg_pass_rate": 54.36,
    "rank": 74,
    "rank_total": 75,
    "best_model": "TRAX 2014",
    "best_model_pass_rate": 73.03,
    "worst_model": "LACETTI 2006",
    "worst_model_pass_rate": 40.22,
    "vs_national": -17.15,
    "vs_national_note": "Manufacturer average vs overall national average (for brand-level comparison)"
  },
  "core_models": [
    {
      "core_model": "TRAX",
      "total_tests": 1513,
      "total_passes": 1033,
      "total_fails": 400,
      "pass_rate": 68.27,
      "avg_mileage": 74090.0,
      "year_from": 2013,
      "year_to": 2014,
      "variant_count": 4,
      "variants": "TRAX"
    },
    {
      "core_model": "CRUZE",
      "total_tests": 5453,
      "total_passes": 3286,
      "total_fails": 1636,
      "pass_rate": 60.26,
      "avg_mileage": 83203.0,
      "year_from": 2009,
      "year_to": 2014,
      "variant_count": 10,
      "variants": "CRUZE"
    },
    {
      "core_model": "ORLANDO",
      "total_tests": 4312,
      "total_passes": 2534,
      "total_fails": 1382,
      "pass_rate": 58.77,
      "avg_mileage": 89353.0,
      "year_from": 2011,
      "year_to": 2014,
      "variant_count": 7,
      "variants": "ORLANDO"
    },
    {
      "core_model": "SPARK",
      "total_tests": 15760,
      "total_passes": 8728,
      "total_fails": 5455,
      "pass_rate": 55.38,
      "avg_mileage": 62612.0,
      "year_from": 2010,
      "year_to": 2014,
      "variant_count": 5,
      "variants": "SPARK"
    },
    {
      "core_model": "CAPTIVA",
      "total_tests": 7078,
      "total_passes": 3766,
      "total_fails": 2775,
      "pass_rate": 53.21,
      "avg_mileage": 99168.0,
      "year_from": 2007,
      "year_to": 2014,
      "variant_count": 8,
      "variants": "CAPTIVA"
    },
    {
      "core_model": "MATIZ",
      "total_tests": 12053,
      "total_passes": 6188,
      "total_fails": 4913,
      "pass_rate": 51.34,
      "avg_mileage": 55478.0,
      "year_from": 2005,
      "year_to": 2010,
      "variant_count": 6,
      "variants": "MATIZ"
    },
    {
      "core_model": "TACUMA",
      "total_tests": 280,
      "total_passes": 140,
      "total_fails": 122,
      "pass_rate": 50.0,
      "avg_mileage": 69009.0,
      "year_from": 2007,
      "year_to": 2008,
      "variant_count": 2,
      "variants": "TACUMA"
    },
    {
      "core_model": "AVEO",
      "total_tests": 9982,
      "total_passes": 4948,
      "total_fails": 4233,
      "pass_rate": 49.57,
      "avg_mileage": 68992.0,
      "year_from": 2008,
      "year_to": 2014,
      "variant_count": 9,
      "variants": "AVEO"
    },
    {
      "core_model": "KALOS",
      "total_tests": 3192,
      "total_passes": 1509,
      "total_fails": 1437,
      "pass_rate": 47.27,
      "avg_mileage": 66563.0,
      "year_from": 2005,
      "year_to": 2008,
      "variant_count": 4,
      "variants": "KALOS"
    },
    {
      "core_model": "LACETTI",
      "total_tests": 2715,
      "total_passes": 1278,
      "total_fails": 1194,
      "pass_rate": 47.07,
      "avg_mileage": 74559.0,
      "year_from": 2005,
      "year_to": 2011,
      "variant_count": 7,
      "variants": "LACETTI"
    }
  ],
  "model_year_breakdowns": {
    "TRAX": [
      {
        "model_year": 2014,
        "fuel_type": "DI",
        "total_tests": 158,
        "pass_rate": 70.89,
        "avg_mileage": 78647.0,
        "pass_rate_vs_national": -0.82,
        "national_avg_for_year": 71.71
      },
      {
        "model_year": 2014,
        "fuel_type": "PE",
        "total_tests": 349,
        "pass_rate": 73.93,
        "avg_mileage": 64193.0,
        "pass_rate_vs_national": 2.22,
        "national_avg_for_year": 71.71
      },
      {
        "model_year": 2013,
        "fuel_type": "DI",
        "total_tests": 510,
        "pass_rate": 61.96,
        "avg_mileage": 85142.0,
        "pass_rate_vs_national": -6.33,
        "national_avg_for_year": 68.29
      },
      {
        "model_year": 2013,
        "fuel_type": "PE",
        "total_tests": 496,
        "pass_rate": 69.96,
        "avg_mileage": 68377.0,
        "pass_rate_vs_national": 1.67,
        "national_avg_for_year": 68.29
      }
    ],
    "CRUZE": [
      {
        "model_year": 2014,
        "fuel_type": "DI",
        "total_tests": 295,
        "pass_rate": 57.63,
        "avg_mileage": 83827.0,
        "pass_rate_vs_national": -14.08,
        "national_avg_for_year": 71.71
      },
      {
        "model_year": 2014,
        "fuel_type": "PE",
        "total_tests": 211,
        "pass_rate": 63.03,
        "avg_mileage": 69409.0,
        "pass_rate_vs_national": -8.68,
        "national_avg_for_year": 71.71
      },
      {
        "model_year": 2013,
        "fuel_type": "DI",
        "total_tests": 359,
        "pass_rate": 61.0,
        "avg_mileage": 96774.0,
        "pass_rate_vs_national": -7.29,
        "national_avg_for_year": 68.29
      },
      {
        "model_year": 2013,
        "fuel_type": "PE",
        "total_tests": 988,
        "pass_rate": 62.15,
        "avg_mileage": 71145.0,
        "pass_rate_vs_national": -6.14,
        "national_avg_for_year": 68.29
      },
      {
        "model_year": 2012,
        "fuel_type": "DI",
        "total_tests": 468,
        "pass_rate": 57.48,
        "avg_mileage": 96424.0,
        "pass_rate_vs_national": -8.15,
        "national_avg_for_year": 65.63
      },
      {
        "model_year": 2012,
        "fuel_type": "PE",
        "total_tests": 1182,
        "pass_rate": 61.51,
        "avg_mileage": 72956.0,
        "pass_rate_vs_national": -4.12,
        "national_avg_for_year": 65.63
      },
      {
        "model_year": 2011,
        "fuel_type": "PE",
        "total_tests": 1023,
        "pass_rate": 62.56,
        "avg_mileage": 75961.0,
        "pass_rate_vs_national": -0.43,
        "national_avg_for_year": 62.99
      },
      {
        "model_year": 2010,
        "fuel_type": "DI",
        "total_tests": 209,
        "pass_rate": 51.67,
        "avg_mileage": 103472.0,
        "pass_rate_vs_national": -8.83,
        "national_avg_for_year": 60.5
      },
      {
        "model_year": 2010,
        "fuel_type": "PE",
        "total_tests": 508,
        "pass_rate": 55.91,
        "avg_mileage": 80593.0,
        "pass_rate_vs_national": -4.59,
        "national_avg_for_year": 60.5
      },
      {
        "model_year": 2009,
        "fuel_type": "PE",
        "total_tests": 210,
        "pass_rate": 58.1,
        "avg_mileage": 81470.0,
        "pass_rate_vs_national": -0.91,
        "national_avg_for_year": 59.01
      }
    ],
    "ORLANDO": [
      {
        "model_year": 2014,
        "fuel_type": "DI",
        "total_tests": 158,
        "pass_rate": 65.82,
        "avg_mileage": 91148.0,
        "pass_rate_vs_national": -5.89,
        "national_avg_for_year": 71.71
      },
      {
        "model_year": 2013,
        "fuel_type": "DI",
        "total_tests": 478,
        "pass_rate": 57.53,
        "avg_mileage": 90223.0,
        "pass_rate_vs_national": -10.76,
        "national_avg_for_year": 68.29
      },
      {
        "model_year": 2013,
        "fuel_type": "PE",
        "total_tests": 357,
        "pass_rate": 61.9,
        "avg_mileage": 79084.0,
        "pass_rate_vs_national": -6.39,
        "national_avg_for_year": 68.29
      },
      {
        "model_year": 2012,
        "fuel_type": "DI",
        "total_tests": 1098,
        "pass_rate": 55.37,
        "avg_mileage": 93207.0,
        "pass_rate_vs_national": -10.26,
        "national_avg_for_year": 65.63
      },
      {
        "model_year": 2012,
        "fuel_type": "PE",
        "total_tests": 854,
        "pass_rate": 60.42,
        "avg_mileage": 79335.0,
        "pass_rate_vs_national": -5.21,
        "national_avg_for_year": 65.63
      },
      {
        "model_year": 2011,
        "fuel_type": "DI",
        "total_tests": 623,
        "pass_rate": 56.82,
        "avg_mileage": 102383.0,
        "pass_rate_vs_national": -6.17,
        "national_avg_for_year": 62.99
      },
      {
        "model_year": 2011,
        "fuel_type": "PE",
        "total_tests": 744,
        "pass_rate": 61.29,
        "avg_mileage": 90093.0,
        "pass_rate_vs_national": -1.7,
        "national_avg_for_year": 62.99
      }
    ],
    "SPARK": [
      {
        "model_year": 2014,
        "fuel_type": "PE",
        "total_tests": 784,
        "pass_rate": 58.67,
        "avg_mileage": 50136.0,
        "pass_rate_vs_national": -13.04,
        "national_avg_for_year": 71.71
      },
      {
        "model_year": 2013,
        "fuel_type": "PE",
        "total_tests": 3962,
        "pass_rate": 54.97,
        "avg_mileage": 61793.0,
        "pass_rate_vs_national": -13.32,
        "national_avg_for_year": 68.29
      },
      {
        "model_year": 2012,
        "fuel_type": "PE",
        "total_tests": 3785,
        "pass_rate": 54.27,
        "avg_mileage": 65637.0,
        "pass_rate_vs_national": -11.36,
        "national_avg_for_year": 65.63
      },
      {
        "model_year": 2011,
        "fuel_type": "PE",
        "total_tests": 3881,
        "pass_rate": 54.55,
        "avg_mileage": 67091.0,
        "pass_rate_vs_national": -8.44,
        "national_avg_for_year": 62.99
      },
      {
        "model_year": 2010,
        "fuel_type": "PE",
        "total_tests": 3348,
        "pass_rate": 57.32,
        "avg_mileage": 68401.0,
        "pass_rate_vs_national": -3.18,
        "national_avg_for_year": 60.5
      }
    ],
    "CAPTIVA": [
      {
        "model_year": 2014,
        "fuel_type": "DI",
        "total_tests": 177,
        "pass_rate": 70.06,
        "avg_mileage": 81656.0,
        "pass_rate_vs_national": -1.65,
        "national_avg_for_year": 71.71
      },
      {
        "model_year": 2013,
        "fuel_type": "DI",
        "total_tests": 1055,
        "pass_rate": 58.86,
        "avg_mileage": 84637.0,
        "pass_rate_vs_national": -9.43,
        "national_avg_for_year": 68.29
      },
      {
        "model_year": 2012,
        "fuel_type": "DI",
        "total_tests": 1022,
        "pass_rate": 55.77,
        "avg_mileage": 89717.0,
        "pass_rate_vs_national": -9.86,
        "national_avg_for_year": 65.63
      },
      {
        "model_year": 2011,
        "fuel_type": "DI",
        "total_tests": 1253,
        "pass_rate": 53.55,
        "avg_mileage": 97038.0,
        "pass_rate_vs_national": -9.44,
        "national_avg_for_year": 62.99
      },
      {
        "model_year": 2010,
        "fuel_type": "DI",
        "total_tests": 1816,
        "pass_rate": 49.5,
        "avg_mileage": 106488.0,
        "pass_rate_vs_national": -11.0,
        "national_avg_for_year": 60.5
      },
      {
        "model_year": 2009,
        "fuel_type": "DI",
        "total_tests": 788,
        "pass_rate": 49.24,
        "avg_mileage": 107389.0,
        "pass_rate_vs_national": -9.77,
        "national_avg_for_year": 59.01
      },
      {
        "model_year": 2008,
        "fuel_type": "DI",
        "total_tests": 734,
        "pass_rate": 50.41,
        "avg_mileage": 113866.0,
        "pass_rate_vs_national": -6.98,
        "national_avg_for_year": 57.39
      },
      {
        "model_year": 2007,
        "fuel_type": "DI",
        "total_tests": 233,
        "pass_rate": 52.79,
        "avg_mileage": 112556.0,
        "pass_rate_vs_national": -4.18,
        "national_avg_for_year": 56.97
      }
    ],
    "MATIZ": [
      {
        "model_year": 2010,
        "fuel_type": "PE",
        "total_tests": 981,
        "pass_rate": 53.31,
        "avg_mileage": 52049.0,
        "pass_rate_vs_national": -7.19,
        "national_avg_for_year": 60.5
      },
      {
        "model_year": 2009,
        "fuel_type": "PE",
        "total_tests": 3911,
        "pass_rate": 53.69,
        "avg_mileage": 51958.0,
        "pass_rate_vs_national": -5.32,
        "national_avg_for_year": 59.01
      },
      {
        "model_year": 2008,
        "fuel_type": "PE",
        "total_tests": 2534,
        "pass_rate": 52.21,
        "avg_mileage": 56326.0,
        "pass_rate_vs_national": -5.18,
        "national_avg_for_year": 57.39
      },
      {
        "model_year": 2007,
        "fuel_type": "PE",
        "total_tests": 2431,
        "pass_rate": 49.36,
        "avg_mileage": 56714.0,
        "pass_rate_vs_national": -7.61,
        "national_avg_for_year": 56.97
      },
      {
        "model_year": 2006,
        "fuel_type": "PE",
        "total_tests": 1463,
        "pass_rate": 48.46,
        "avg_mileage": 57294.0,
        "pass_rate_vs_national": -7.72,
        "national_avg_for_year": 56.18
      },
      {
        "model_year": 2005,
        "fuel_type": "PE",
        "total_tests": 733,
        "pass_rate": 45.43,
        "avg_mileage": 58528.0,
        "pass_rate_vs_national": -10.82,
        "national_avg_for_year": 56.25
      }
    ],
    "TACUMA": [
      {
        "model_year": 2008,
        "fuel_type": "PE",
        "total_tests": 103,
        "pass_rate": 49.51,
        "avg_mileage": 66851.0,
        "pass_rate_vs_national": -7.88,
        "national_avg_for_year": 57.39
      },
      {
        "model_year": 2007,
        "fuel_type": "PE",
        "total_tests": 177,
        "pass_rate": 50.28,
        "avg_mileage": 71166.0,
        "pass_rate_vs_national": -6.69,
        "national_avg_for_year": 56.97
      }
    ],
    "AVEO": [
      {
        "model_year": 2014,
        "fuel_type": "PE",
        "total_tests": 114,
        "pass_rate": 66.67,
        "avg_mileage": 53433.0,
        "pass_rate_vs_national": -5.04,
        "national_avg_for_year": 71.71
      },
      {
        "model_year": 2013,
        "fuel_type": "DI",
        "total_tests": 259,
        "pass_rate": 50.58,
        "avg_mileage": 78778.0,
        "pass_rate_vs_national": -17.71,
        "national_avg_for_year": 68.29
      },
      {
        "model_year": 2013,
        "fuel_type": "PE",
        "total_tests": 1099,
        "pass_rate": 58.14,
        "avg_mileage": 62582.0,
        "pass_rate_vs_national": -10.15,
        "national_avg_for_year": 68.29
      },
      {
        "model_year": 2012,
        "fuel_type": "DI",
        "total_tests": 413,
        "pass_rate": 47.22,
        "avg_mileage": 85737.0,
        "pass_rate_vs_national": -18.41,
        "national_avg_for_year": 65.63
      },
      {
        "model_year": 2012,
        "fuel_type": "PE",
        "total_tests": 1121,
        "pass_rate": 54.86,
        "avg_mileage": 65327.0,
        "pass_rate_vs_national": -10.77,
        "national_avg_for_year": 65.63
      },
      {
        "model_year": 2011,
        "fuel_type": "PE",
        "total_tests": 1210,
        "pass_rate": 51.65,
        "avg_mileage": 63293.0,
        "pass_rate_vs_national": -11.34,
        "national_avg_for_year": 62.99
      },
      {
        "model_year": 2010,
        "fuel_type": "PE",
        "total_tests": 1523,
        "pass_rate": 47.08,
        "avg_mileage": 69173.0,
        "pass_rate_vs_national": -13.42,
        "national_avg_for_year": 60.5
      },
      {
        "model_year": 2009,
        "fuel_type": "PE",
        "total_tests": 3352,
        "pass_rate": 46.09,
        "avg_mileage": 70797.0,
        "pass_rate_vs_national": -12.92,
        "national_avg_for_year": 59.01
      },
      {
        "model_year": 2008,
        "fuel_type": "PE",
        "total_tests": 891,
        "pass_rate": 45.45,
        "avg_mileage": 71807.0,
        "pass_rate_vs_national": -11.94,
        "national_avg_for_year": 57.39
      }
    ],
    "KALOS": [
      {
        "model_year": 2008,
        "fuel_type": "PE",
        "total_tests": 819,
        "pass_rate": 48.35,
        "avg_mileage": 61942.0,
        "pass_rate_vs_national": -9.04,
        "national_avg_for_year": 57.39
      },
      {
        "model_year": 2007,
        "fuel_type": "PE",
        "total_tests": 1106,
        "pass_rate": 48.55,
        "avg_mileage": 66720.0,
        "pass_rate_vs_national": -8.42,
        "national_avg_for_year": 56.97
      },
      {
        "model_year": 2006,
        "fuel_type": "PE",
        "total_tests": 688,
        "pass_rate": 47.97,
        "avg_mileage": 68335.0,
        "pass_rate_vs_national": -8.21,
        "national_avg_for_year": 56.18
      },
      {
        "model_year": 2005,
        "fuel_type": "PE",
        "total_tests": 579,
        "pass_rate": 42.49,
        "avg_mileage": 69255.0,
        "pass_rate_vs_national": -13.76,
        "national_avg_for_year": 56.25
      }
    ],
    "LACETTI": [
      {
        "model_year": 2011,
        "fuel_type": "PE",
        "total_tests": 120,
        "pass_rate": 48.33,
        "avg_mileage": 74406.0,
        "pass_rate_vs_national": -14.66,
        "national_avg_for_year": 62.99
      },
      {
        "model_year": 2010,
        "fuel_type": "PE",
        "total_tests": 249,
        "pass_rate": 51.81,
        "avg_mileage": 73827.0,
        "pass_rate_vs_national": -8.69,
        "national_avg_for_year": 60.5
      },
      {
        "model_year": 2009,
        "fuel_type": "PE",
        "total_tests": 639,
        "pass_rate": 49.77,
        "avg_mileage": 75371.0,
        "pass_rate_vs_national": -9.24,
        "national_avg_for_year": 59.01
      },
      {
        "model_year": 2008,
        "fuel_type": "PE",
        "total_tests": 658,
        "pass_rate": 47.72,
        "avg_mileage": 74110.0,
        "pass_rate_vs_national": -9.67,
        "national_avg_for_year": 57.39
      },
      {
        "model_year": 2007,
        "fuel_type": "PE",
        "total_tests": 483,
        "pass_rate": 45.96,
        "avg_mileage": 77474.0,
        "pass_rate_vs_national": -11.01,
        "national_avg_for_year": 56.97
      },
      {
        "model_year": 2006,
        "fuel_type": "PE",
        "total_tests": 368,
        "pass_rate": 40.22,
        "avg_mileage": 75610.0,
        "pass_rate_vs_national": -15.96,
        "national_avg_for_year": 56.18
      },
      {
        "model_year": 2005,
        "fuel_type": "PE",
        "total_tests": 198,
        "pass_rate": 44.95,
        "avg_mileage": 71116.0,
        "pass_rate_vs_national": -11.3,
        "national_avg_for_year": 56.25
      }
    ]
  },
  "fuel_analysis": [
    {
      "fuel_type": "DI",
      "model_count": 20,
      "total_tests": 12106,
      "pass_rate": 54.74,
      "fuel_name": "Diesel"
    },
    {
      "fuel_type": "PE",
      "model_count": 42,
      "total_tests": 50232,
      "pass_rate": 53.32,
      "fuel_name": "Petrol"
    }
  ],
  "best_models": [
    {
      "model": "TRAX",
      "model_year": 2014,
      "fuel_type": "PE",
      "total_tests": 349,
      "pass_rate": 73.93,
      "pass_rate_vs_national": 2.22,
      "national_avg_for_year": 71.71
    },
    {
      "model": "TRAX",
      "model_year": 2013,
      "fuel_type": "PE",
      "total_tests": 496,
      "pass_rate": 69.96,
      "pass_rate_vs_national": 1.67,
      "national_avg_for_year": 68.29
    },
    {
      "model": "CRUZE",
      "model_year": 2011,
      "fuel_type": "PE",
      "total_tests": 1023,
      "pass_rate": 62.56,
      "pass_rate_vs_national": -0.43,
      "national_avg_for_year": 62.99
    },
    {
      "model": "TRAX",
      "model_year": 2014,
      "fuel_type": "DI",
      "total_tests": 158,
      "pass_rate": 70.89,
      "pass_rate_vs_national": -0.82,
      "national_avg_for_year": 71.71
    },
    {
      "model": "CRUZE",
      "model_year": 2009,
      "fuel_type": "PE",
      "total_tests": 210,
      "pass_rate": 58.1,
      "pass_rate_vs_national": -0.91,
      "national_avg_for_year": 59.01
    },
    {
      "model": "CAPTIVA",
      "model_year": 2014,
      "fuel_type": "DI",
      "total_tests": 177,
      "pass_rate": 70.06,
      "pass_rate_vs_national": -1.65,
      "national_avg_for_year": 71.71
    },
    {
      "model": "ORLANDO",
      "model_year": 2011,
      "fuel_type": "PE",
      "total_tests": 744,
      "pass_rate": 61.29,
      "pass_rate_vs_national": -1.7,
      "national_avg_for_year": 62.99
    },
    {
      "model": "SPARK",
      "model_year": 2010,
      "fuel_type": "PE",
      "total_tests": 3348,
      "pass_rate": 57.32,
      "pass_rate_vs_national": -3.18,
      "national_avg_for_year": 60.5
    },
    {
      "model": "CRUZE",
      "model_year": 2012,
      "fuel_type": "PE",
      "total_tests": 1182,
      "pass_rate": 61.51,
      "pass_rate_vs_national": -4.12,
      "national_avg_for_year": 65.63
    },
    {
      "model": "CAPTIVA",
      "model_year": 2007,
      "fuel_type": "DI",
      "total_tests": 233,
      "pass_rate": 52.79,
      "pass_rate_vs_national": -4.18,
      "national_avg_for_year": 56.97
    },
    {
      "model": "CRUZE",
      "model_year": 2010,
      "fuel_type": "PE",
      "total_tests": 508,
      "pass_rate": 55.91,
      "pass_rate_vs_national": -4.59,
      "national_avg_for_year": 60.5
    },
    {
      "model": "AVEO",
      "model_year": 2014,
      "fuel_type": "PE",
      "total_tests": 114,
      "pass_rate": 66.67,
      "pass_rate_vs_national": -5.04,
      "national_avg_for_year": 71.71
    },
    {
      "model": "MATIZ",
      "model_year": 2008,
      "fuel_type": "PE",
      "total_tests": 2534,
      "pass_rate": 52.21,
      "pass_rate_vs_national": -5.18,
      "national_avg_for_year": 57.39
    },
    {
      "model": "ORLANDO",
      "model_year": 2012,
      "fuel_type": "PE",
      "total_tests": 854,
      "pass_rate": 60.42,
      "pass_rate_vs_national": -5.21,
      "national_avg_for_year": 65.63
    },
    {
      "model": "MATIZ",
      "model_year": 2009,
      "fuel_type": "PE",
      "total_tests": 3911,
      "pass_rate": 53.69,
      "pass_rate_vs_national": -5.32,
      "national_avg_for_year": 59.01
    }
  ],
  "worst_models": [
    {
      "model": "AVEO",
      "model_year": 2012,
      "fuel_type": "DI",
      "total_tests": 413,
      "pass_rate": 47.22,
      "pass_rate_vs_national": -18.41,
      "national_avg_for_year": 65.63
    },
    {
      "model": "AVEO",
      "model_year": 2013,
      "fuel_type": "DI",
      "total_tests": 259,
      "pass_rate": 50.58,
      "pass_rate_vs_national": -17.71,
      "national_avg_for_year": 68.29
    },
    {
      "model": "LACETTI",
      "model_year": 2006,
      "fuel_type": "PE",
      "total_tests": 368,
      "pass_rate": 40.22,
      "pass_rate_vs_national": -15.96,
      "national_avg_for_year": 56.18
    },
    {
      "model": "LACETTI",
      "model_year": 2011,
      "fuel_type": "PE",
      "total_tests": 120,
      "pass_rate": 48.33,
      "pass_rate_vs_national": -14.66,
      "national_avg_for_year": 62.99
    },
    {
      "model": "CRUZE",
      "model_year": 2014,
      "fuel_type": "DI",
      "total_tests": 295,
      "pass_rate": 57.63,
      "pass_rate_vs_national": -14.08,
      "national_avg_for_year": 71.71
    },
    {
      "model": "KALOS",
      "model_year": 2005,
      "fuel_type": "PE",
      "total_tests": 579,
      "pass_rate": 42.49,
      "pass_rate_vs_national": -13.76,
      "national_avg_for_year": 56.25
    },
    {
      "model": "AVEO",
      "model_year": 2010,
      "fuel_type": "PE",
      "total_tests": 1523,
      "pass_rate": 47.08,
      "pass_rate_vs_national": -13.42,
      "national_avg_for_year": 60.5
    },
    {
      "model": "SPARK",
      "model_year": 2013,
      "fuel_type": "PE",
      "total_tests": 3962,
      "pass_rate": 54.97,
      "pass_rate_vs_national": -13.32,
      "national_avg_for_year": 68.29
    },
    {
      "model": "SPARK",
      "model_year": 2014,
      "fuel_type": "PE",
      "total_tests": 784,
      "pass_rate": 58.67,
      "pass_rate_vs_national": -13.04,
      "national_avg_for_year": 71.71
    },
    {
      "model": "AVEO",
      "model_year": 2009,
      "fuel_type": "PE",
      "total_tests": 3352,
      "pass_rate": 46.09,
      "pass_rate_vs_national": -12.92,
      "national_avg_for_year": 59.01
    }
  ],
  "failures": {
    "categories": [
      {
        "category_name": "Lamps, reflectors and electrical equipment",
        "total_failures": 13460,
        "vehicle_count": 62
      },
      {
        "category_name": "Suspension",
        "total_failures": 11119,
        "vehicle_count": 62
      },
      {
        "category_name": "Brakes",
        "total_failures": 9820,
        "vehicle_count": 62
      },
      {
        "category_name": "Visibility",
        "total_failures": 5354,
        "vehicle_count": 62
      },
      {
        "category_name": "Tyres",
        "total_failures": 4922,
        "vehicle_count": 62
      },
      {
        "category_name": "Body, chassis, structure",
        "total_failures": 4290,
        "vehicle_count": 62
      },
      {
        "category_name": "Noise, emissions and leaks",
        "total_failures": 3935,
        "vehicle_count": 62
      },
      {
        "category_name": "Steering",
        "total_failures": 2344,
        "vehicle_count": 57
      },
      {
        "category_name": "Seat belts and supplementary restraint systems",
        "total_failures": 1525,
        "vehicle_count": 54
      },
      {
        "category_name": "Identification of the vehicle",
        "total_failures": 347,
        "vehicle_count": 51
      },
      {
        "category_name": "Road Wheels",
        "total_failures": 65,
        "vehicle_count": 18
      }
    ],
    "top_failures": [
      {
        "defect_description": "not working",
        "category_name": "Lamps, reflectors and electrical equipment",
        "total_occurrences": 7032
      },
      {
        "defect_description": "fractured or broken",
        "category_name": "Suspension",
        "total_occurrences": 2598
      },
      {
        "defect_description": "does not clear the windscreen effectively ",
        "category_name": "Visibility",
        "total_occurrences": 2391
      },
      {
        "defect_description": "ball joint excessively worn",
        "category_name": "Suspension",
        "total_occurrences": 2049
      },
      {
        "defect_description": "excessively corroded",
        "category_name": "Brakes",
        "total_occurrences": 1974
      },
      {
        "defect_description": "tread depth below requirements of 1.6mm",
        "category_name": "Tyres",
        "total_occurrences": 1928
      },
      {
        "defect_description": "not working on dipped beam",
        "category_name": "Lamps, reflectors and electrical equipment",
        "total_occurrences": 1732
      },
      {
        "defect_description": "excessively binding",
        "category_name": "Brakes",
        "total_occurrences": 1629
      },
      {
        "defect_description": "pin or bush excessively worn",
        "category_name": "Suspension",
        "total_occurrences": 1254
      },
      {
        "defect_description": "inoperative or indicates a malfunction",
        "category_name": "Noise, emissions and leaks",
        "total_occurrences": 1004
      }
    ],
    "top_advisories": [
      {
        "defect_description": "worn close to legal limit/worn on edge",
        "category_name": "Tyres",
        "total_occurrences": 11813
      },
      {
        "defect_description": "corroded, covered in grease or other material",
        "category_name": "Brakes",
        "total_occurrences": 9954
      },
      {
        "defect_description": "leak, but not excessive",
        "category_name": "Noise, emissions and leaks",
        "total_occurrences": 8535
      },
      {
        "defect_description": "slightly damaged/cracking or perishing",
        "category_name": "Tyres",
        "total_occurrences": 6668
      },
      {
        "defect_description": "pin or bush worn but not resulting in excessive movement",
        "category_name": "Suspension",
        "total_occurrences": 4949
      },
      {
        "defect_description": "worn, pitted or scored, but not seriously weakened",
        "category_name": "Brakes",
        "total_occurrences": 4206
      },
      {
        "defect_description": "has a minor leak of exhaust gases",
        "category_name": "Body, chassis, structure",
        "total_occurrences": 3966
      },
      {
        "defect_description": "wearing thin",
        "category_name": "Brakes",
        "total_occurrences": 3240
      },
      {
        "defect_description": "deteriorated but not likely to be misread",
        "category_name": "Identification of the vehicle",
        "total_occurrences": 2227
      },
      {
        "defect_description": "binding but not excessively",
        "category_name": "Brakes",
        "total_occurrences": 1796
      }
    ],
    "dangerous": [
      {
        "defect_description": "tread depth below requirements of 1.6mm",
        "category_name": "Tyres",
        "total_occurrences": 13124
      },
      {
        "defect_description": "has a tear, caused by separation or partial failure of its structure",
        "category_name": "Tyres",
        "total_occurrences": 7200
      },
      {
        "defect_description": "less than 1.5 mm thick",
        "category_name": "Brakes",
        "total_occurrences": 5550
      },
      {
        "defect_description": "in such a condition that it is seriously weakened",
        "category_name": "Brakes",
        "total_occurrences": 4895
      },
      {
        "defect_description": "tread pattern not visible over the whole tread area when minimum depth required is 1.0mm ",
        "category_name": "Tyres",
        "total_occurrences": 1847
      },
      {
        "defect_description": "has ply or cords exposed",
        "category_name": "Tyres",
        "total_occurrences": 1015
      },
      {
        "defect_description": "webbing significantly weakened",
        "category_name": "Seat belts and supplementary restraint systems",
        "total_occurrences": 901
      },
      {
        "defect_description": "has a bulge, caused by separation or partial failure of its structure",
        "category_name": "Tyres",
        "total_occurrences": 344
      },
      {
        "defect_description": "efficiency less than 50% of the required value",
        "category_name": "Brakes",
        "total_occurrences": 194
      },
      {
        "defect_description": "all not working",
        "category_name": "Lamps, reflectors and electrical equipment",
        "total_occurrences": 154
      }
    ]
  },
  "mileage_impact": [
    {
      "mileage_band": "0-30k",
      "band_order": 0,
      "total_tests": 4137,
      "avg_pass_rate": 69.54
    },
    {
      "mileage_band": "30k-60k",
      "band_order": 1,
      "total_tests": 19699,
      "avg_pass_rate": 57.56
    },
    {
      "mileage_band": "60k-90k",
      "band_order": 2,
      "total_tests": 23100,
      "avg_pass_rate": 50.75
    },
    {
      "mileage_band": "90k-120k",
      "band_order": 3,
      "total_tests": 11187,
      "avg_pass_rate": 48.46
    },
    {
      "mileage_band": "120k-150k",
      "band_order": 4,
      "total_tests": 3002,
      "avg_pass_rate": 48.43
    },
    {
      "mileage_band": "150k+",
      "band_order": 5,
      "total_tests": 744,
      "avg_pass_rate": 48.12
    }
  ],
  "all_models": [
    {
      "model": "TRAX",
      "model_year": 2014,
      "fuel_type": "PE",
      "total_tests": 349,
      "total_passes": 258,
      "total_fails": 78,
      "pass_rate": 73.93,
      "avg_mileage": 64193.0,
      "avg_age_years": 8.6,
      "pass_rate_vs_national": 2.41
    },
    {
      "model": "TRAX",
      "model_year": 2014,
      "fuel_type": "DI",
      "total_tests": 158,
      "total_passes": 112,
      "total_fails": 37,
      "pass_rate": 70.89,
      "avg_mileage": 78647.0,
      "avg_age_years": 8.6,
      "pass_rate_vs_national": -0.62
    },
    {
      "model": "CAPTIVA",
      "model_year": 2014,
      "fuel_type": "DI",
      "total_tests": 177,
      "total_passes": 124,
      "total_fails": 41,
      "pass_rate": 70.06,
      "avg_mileage": 81656.0,
      "avg_age_years": 8.7,
      "pass_rate_vs_national": -1.45
    },
    {
      "model": "TRAX",
      "model_year": 2013,
      "fuel_type": "PE",
      "total_tests": 496,
      "total_passes": 347,
      "total_fails": 125,
      "pass_rate": 69.96,
      "avg_mileage": 68377.0,
      "avg_age_years": 9.2,
      "pass_rate_vs_national": -1.55
    },
    {
      "model": "AVEO",
      "model_year": 2014,
      "fuel_type": "PE",
      "total_tests": 114,
      "total_passes": 76,
      "total_fails": 34,
      "pass_rate": 66.67,
      "avg_mileage": 53433.0,
      "avg_age_years": 8.6,
      "pass_rate_vs_national": -4.84
    },
    {
      "model": "ORLANDO",
      "model_year": 2014,
      "fuel_type": "DI",
      "total_tests": 158,
      "total_passes": 104,
      "total_fails": 48,
      "pass_rate": 65.82,
      "avg_mileage": 91148.0,
      "avg_age_years": 8.6,
      "pass_rate_vs_national": -5.69
    },
    {
      "model": "CRUZE",
      "model_year": 2014,
      "fuel_type": "PE",
      "total_tests": 211,
      "total_passes": 133,
      "total_fails": 58,
      "pass_rate": 63.03,
      "avg_mileage": 69409.0,
      "avg_age_years": 8.6,
      "pass_rate_vs_national": -8.48
    },
    {
      "model": "CRUZE",
      "model_year": 2011,
      "fuel_type": "PE",
      "total_tests": 1023,
      "total_passes": 640,
      "total_fails": 281,
      "pass_rate": 62.56,
      "avg_mileage": 75961.0,
      "avg_age_years": 11.4,
      "pass_rate_vs_national": -8.95
    },
    {
      "model": "CRUZE",
      "model_year": 2013,
      "fuel_type": "PE",
      "total_tests": 988,
      "total_passes": 614,
      "total_fails": 284,
      "pass_rate": 62.15,
      "avg_mileage": 71145.0,
      "avg_age_years": 9.5,
      "pass_rate_vs_national": -9.37
    },
    {
      "model": "TRAX",
      "model_year": 2013,
      "fuel_type": "DI",
      "total_tests": 510,
      "total_passes": 316,
      "total_fails": 160,
      "pass_rate": 61.96,
      "avg_mileage": 85142.0,
      "avg_age_years": 9.3,
      "pass_rate_vs_national": -9.55
    },
    {
      "model": "ORLANDO",
      "model_year": 2013,
      "fuel_type": "PE",
      "total_tests": 357,
      "total_passes": 221,
      "total_fails": 105,
      "pass_rate": 61.9,
      "avg_mileage": 79084.0,
      "avg_age_years": 9.5,
      "pass_rate_vs_national": -9.61
    },
    {
      "model": "CRUZE",
      "model_year": 2012,
      "fuel_type": "PE",
      "total_tests": 1182,
      "total_passes": 727,
      "total_fails": 325,
      "pass_rate": 61.51,
      "avg_mileage": 72956.0,
      "avg_age_years": 10.6,
      "pass_rate_vs_national": -10.0
    },
    {
      "model": "ORLANDO",
      "model_year": 2011,
      "fuel_type": "PE",
      "total_tests": 744,
      "total_passes": 456,
      "total_fails": 217,
      "pass_rate": 61.29,
      "avg_mileage": 90093.0,
      "avg_age_years": 11.4,
      "pass_rate_vs_national": -10.22
    },
    {
      "model": "CRUZE",
      "model_year": 2013,
      "fuel_type": "DI",
      "total_tests": 359,
      "total_passes": 219,
      "total_fails": 111,
      "pass_rate": 61.0,
      "avg_mileage": 96774.0,
      "avg_age_years": 9.5,
      "pass_rate_vs_national": -10.51
    },
    {
      "model": "ORLANDO",
      "model_year": 2012,
      "fuel_type": "PE",
      "total_tests": 854,
      "total_passes": 516,
      "total_fails": 249,
      "pass_rate": 60.42,
      "avg_mileage": 79335.0,
      "avg_age_years": 10.5,
      "pass_rate_vs_national": -11.09
    },
    {
      "model": "CAPTIVA",
      "model_year": 2013,
      "fuel_type": "DI",
      "total_tests": 1055,
      "total_passes": 621,
      "total_fails": 353,
      "pass_rate": 58.86,
      "avg_mileage": 84637.0,
      "avg_age_years": 9.5,
      "pass_rate_vs_national": -12.65
    },
    {
      "model": "SPARK",
      "model_year": 2014,
      "fuel_type": "PE",
      "total_tests": 784,
      "total_passes": 460,
      "total_fails": 259,
      "pass_rate": 58.67,
      "avg_mileage": 50136.0,
      "avg_age_years": 8.6,
      "pass_rate_vs_national": -12.84
    },
    {
      "model": "AVEO",
      "model_year": 2013,
      "fuel_type": "PE",
      "total_tests": 1099,
      "total_passes": 639,
      "total_fails": 390,
      "pass_rate": 58.14,
      "avg_mileage": 62582.0,
      "avg_age_years": 9.6,
      "pass_rate_vs_national": -13.37
    },
    {
      "model": "CRUZE",
      "model_year": 2009,
      "fuel_type": "PE",
      "total_tests": 210,
      "total_passes": 122,
      "total_fails": 68,
      "pass_rate": 58.1,
      "avg_mileage": 81470.0,
      "avg_age_years": 13.3,
      "pass_rate_vs_national": -13.42
    },
    {
      "model": "CRUZE",
      "model_year": 2014,
      "fuel_type": "DI",
      "total_tests": 295,
      "total_passes": 170,
      "total_fails": 95,
      "pass_rate": 57.63,
      "avg_mileage": 83827.0,
      "avg_age_years": 8.6,
      "pass_rate_vs_national": -13.88
    },
    {
      "model": "ORLANDO",
      "model_year": 2013,
      "fuel_type": "DI",
      "total_tests": 478,
      "total_passes": 275,
      "total_fails": 163,
      "pass_rate": 57.53,
      "avg_mileage": 90223.0,
      "avg_age_years": 9.5,
      "pass_rate_vs_national": -13.98
    },
    {
      "model": "CRUZE",
      "model_year": 2012,
      "fuel_type": "DI",
      "total_tests": 468,
      "total_passes": 269,
      "total_fails": 161,
      "pass_rate": 57.48,
      "avg_mileage": 96424.0,
      "avg_age_years": 10.4,
      "pass_rate_vs_national": -14.03
    },
    {
      "model": "SPARK",
      "model_year": 2010,
      "fuel_type": "PE",
      "total_tests": 3348,
      "total_passes": 1919,
      "total_fails": 1090,
      "pass_rate": 57.32,
      "avg_mileage": 68401.0,
      "avg_age_years": 12.4,
      "pass_rate_vs_national": -14.19
    },
    {
      "model": "ORLANDO",
      "model_year": 2011,
      "fuel_type": "DI",
      "total_tests": 623,
      "total_passes": 354,
      "total_fails": 218,
      "pass_rate": 56.82,
      "avg_mileage": 102383.0,
      "avg_age_years": 11.5,
      "pass_rate_vs_national": -14.69
    },
    {
      "model": "CRUZE",
      "model_year": 2010,
      "fuel_type": "PE",
      "total_tests": 508,
      "total_passes": 284,
      "total_fails": 173,
      "pass_rate": 55.91,
      "avg_mileage": 80593.0,
      "avg_age_years": 12.4,
      "pass_rate_vs_national": -15.61
    },
    {
      "model": "CAPTIVA",
      "model_year": 2012,
      "fuel_type": "DI",
      "total_tests": 1022,
      "total_passes": 570,
      "total_fails": 378,
      "pass_rate": 55.77,
      "avg_mileage": 89717.0,
      "avg_age_years": 10.6,
      "pass_rate_vs_national": -15.74
    },
    {
      "model": "ORLANDO",
      "model_year": 2012,
      "fuel_type": "DI",
      "total_tests": 1098,
      "total_passes": 608,
      "total_fails": 382,
      "pass_rate": 55.37,
      "avg_mileage": 93207.0,
      "avg_age_years": 10.6,
      "pass_rate_vs_national": -16.14
    },
    {
      "model": "SPARK",
      "model_year": 2013,
      "fuel_type": "PE",
      "total_tests": 3962,
      "total_passes": 2178,
      "total_fails": 1433,
      "pass_rate": 54.97,
      "avg_mileage": 61793.0,
      "avg_age_years": 9.5,
      "pass_rate_vs_national": -16.54
    },
    {
      "model": "AVEO",
      "model_year": 2012,
      "fuel_type": "PE",
      "total_tests": 1121,
      "total_passes": 615,
      "total_fails": 416,
      "pass_rate": 54.86,
      "avg_mileage": 65327.0,
      "avg_age_years": 10.5,
      "pass_rate_vs_national": -16.65
    },
    {
      "model": "SPARK",
      "model_year": 2011,
      "fuel_type": "PE",
      "total_tests": 3881,
      "total_passes": 2117,
      "total_fails": 1363,
      "pass_rate": 54.55,
      "avg_mileage": 67091.0,
      "avg_age_years": 11.5,
      "pass_rate_vs_national": -16.96
    },
    {
      "model": "SPARK",
      "model_year": 2012,
      "fuel_type": "PE",
      "total_tests": 3785,
      "total_passes": 2054,
      "total_fails": 1310,
      "pass_rate": 54.27,
      "avg_mileage": 65637.0,
      "avg_age_years": 10.6,
      "pass_rate_vs_national": -17.24
    },
    {
      "model": "MATIZ",
      "model_year": 2009,
      "fuel_type": "PE",
      "total_tests": 3911,
      "total_passes": 2100,
      "total_fails": 1491,
      "pass_rate": 53.69,
      "avg_mileage": 51958.0,
      "avg_age_years": 13.4,
      "pass_rate_vs_national": -17.82
    },
    {
      "model": "CAPTIVA",
      "model_year": 2011,
      "fuel_type": "DI",
      "total_tests": 1253,
      "total_passes": 671,
      "total_fails": 494,
      "pass_rate": 53.55,
      "avg_mileage": 97038.0,
      "avg_age_years": 11.6,
      "pass_rate_vs_national": -17.96
    },
    {
      "model": "MATIZ",
      "model_year": 2010,
      "fuel_type": "PE",
      "total_tests": 981,
      "total_passes": 523,
      "total_fails": 381,
      "pass_rate": 53.31,
      "avg_mileage": 52049.0,
      "avg_age_years": 12.7,
      "pass_rate_vs_national": -18.2
    },
    {
      "model": "CAPTIVA",
      "model_year": 2007,
      "fuel_type": "DI",
      "total_tests": 233,
      "total_passes": 123,
      "total_fails": 94,
      "pass_rate": 52.79,
      "avg_mileage": 112556.0,
      "avg_age_years": 15.3,
      "pass_rate_vs_national": -18.72
    },
    {
      "model": "MATIZ",
      "model_year": 2008,
      "fuel_type": "PE",
      "total_tests": 2534,
      "total_passes": 1323,
      "total_fails": 1007,
      "pass_rate": 52.21,
      "avg_mileage": 56326.0,
      "avg_age_years": 14.4,
      "pass_rate_vs_national": -19.3
    },
    {
      "model": "LACETTI",
      "model_year": 2010,
      "fuel_type": "PE",
      "total_tests": 249,
      "total_passes": 129,
      "total_fails": 100,
      "pass_rate": 51.81,
      "avg_mileage": 73827.0,
      "avg_age_years": 12.5,
      "pass_rate_vs_national": -19.7
    },
    {
      "model": "CRUZE",
      "model_year": 2010,
      "fuel_type": "DI",
      "total_tests": 209,
      "total_passes": 108,
      "total_fails": 80,
      "pass_rate": 51.67,
      "avg_mileage": 103472.0,
      "avg_age_years": 12.5,
      "pass_rate_vs_national": -19.84
    },
    {
      "model": "AVEO",
      "model_year": 2011,
      "fuel_type": "PE",
      "total_tests": 1210,
      "total_passes": 625,
      "total_fails": 499,
      "pass_rate": 51.65,
      "avg_mileage": 63293.0,
      "avg_age_years": 11.6,
      "pass_rate_vs_national": -19.86
    },
    {
      "model": "AVEO",
      "model_year": 2013,
      "fuel_type": "DI",
      "total_tests": 259,
      "total_passes": 131,
      "total_fails": 114,
      "pass_rate": 50.58,
      "avg_mileage": 78778.0,
      "avg_age_years": 9.6,
      "pass_rate_vs_national": -20.93
    },
    {
      "model": "CAPTIVA",
      "model_year": 2008,
      "fuel_type": "DI",
      "total_tests": 734,
      "total_passes": 370,
      "total_fails": 303,
      "pass_rate": 50.41,
      "avg_mileage": 113866.0,
      "avg_age_years": 14.5,
      "pass_rate_vs_national": -21.1
    },
    {
      "model": "TACUMA",
      "model_year": 2007,
      "fuel_type": "PE",
      "total_tests": 177,
      "total_passes": 89,
      "total_fails": 79,
      "pass_rate": 50.28,
      "avg_mileage": 71166.0,
      "avg_age_years": 15.5,
      "pass_rate_vs_national": -21.23
    },
    {
      "model": "LACETTI",
      "model_year": 2009,
      "fuel_type": "PE",
      "total_tests": 639,
      "total_passes": 318,
      "total_fails": 257,
      "pass_rate": 49.77,
      "avg_mileage": 75371.0,
      "avg_age_years": 13.5,
      "pass_rate_vs_national": -21.75
    },
    {
      "model": "TACUMA",
      "model_year": 2008,
      "fuel_type": "PE",
      "total_tests": 103,
      "total_passes": 51,
      "total_fails": 43,
      "pass_rate": 49.51,
      "avg_mileage": 66851.0,
      "avg_age_years": 14.6,
      "pass_rate_vs_national": -22.0
    },
    {
      "model": "CAPTIVA",
      "model_year": 2010,
      "fuel_type": "DI",
      "total_tests": 1816,
      "total_passes": 899,
      "total_fails": 776,
      "pass_rate": 49.5,
      "avg_mileage": 106488.0,
      "avg_age_years": 12.4,
      "pass_rate_vs_national": -22.01
    },
    {
      "model": "MATIZ",
      "model_year": 2007,
      "fuel_type": "PE",
      "total_tests": 2431,
      "total_passes": 1200,
      "total_fails": 1044,
      "pass_rate": 49.36,
      "avg_mileage": 56714.0,
      "avg_age_years": 15.4,
      "pass_rate_vs_national": -22.15
    },
    {
      "model": "CAPTIVA",
      "model_year": 2009,
      "fuel_type": "DI",
      "total_tests": 788,
      "total_passes": 388,
      "total_fails": 336,
      "pass_rate": 49.24,
      "avg_mileage": 107389.0,
      "avg_age_years": 13.5,
      "pass_rate_vs_national": -22.27
    },
    {
      "model": "KALOS",
      "model_year": 2007,
      "fuel_type": "PE",
      "total_tests": 1106,
      "total_passes": 537,
      "total_fails": 477,
      "pass_rate": 48.55,
      "avg_mileage": 66720.0,
      "avg_age_years": 15.5,
      "pass_rate_vs_national": -22.96
    },
    {
      "model": "MATIZ",
      "model_year": 2006,
      "fuel_type": "PE",
      "total_tests": 1463,
      "total_passes": 709,
      "total_fails": 647,
      "pass_rate": 48.46,
      "avg_mileage": 57294.0,
      "avg_age_years": 16.4,
      "pass_rate_vs_national": -23.05
    },
    {
      "model": "KALOS",
      "model_year": 2008,
      "fuel_type": "PE",
      "total_tests": 819,
      "total_passes": 396,
      "total_fails": 371,
      "pass_rate": 48.35,
      "avg_mileage": 61942.0,
      "avg_age_years": 14.6,
      "pass_rate_vs_national": -23.16
    },
    {
      "model": "LACETTI",
      "model_year": 2011,
      "fuel_type": "PE",
      "total_tests": 120,
      "total_passes": 58,
      "total_fails": 49,
      "pass_rate": 48.33,
      "avg_mileage": 74406.0,
      "avg_age_years": 11.6,
      "pass_rate_vs_national": -23.18
    },
    {
      "model": "KALOS",
      "model_year": 2006,
      "fuel_type": "PE",
      "total_tests": 688,
      "total_passes": 330,
      "total_fails": 304,
      "pass_rate": 47.97,
      "avg_mileage": 68335.0,
      "avg_age_years": 16.5,
      "pass_rate_vs_national": -23.55
    },
    {
      "model": "LACETTI",
      "model_year": 2008,
      "fuel_type": "PE",
      "total_tests": 658,
      "total_passes": 314,
      "total_fails": 280,
      "pass_rate": 47.72,
      "avg_mileage": 74110.0,
      "avg_age_years": 14.5,
      "pass_rate_vs_national": -23.79
    },
    {
      "model": "AVEO",
      "model_year": 2012,
      "fuel_type": "DI",
      "total_tests": 413,
      "total_passes": 195,
      "total_fails": 189,
      "pass_rate": 47.22,
      "avg_mileage": 85737.0,
      "avg_age_years": 10.5,
      "pass_rate_vs_national": -24.3
    },
    {
      "model": "AVEO",
      "model_year": 2010,
      "fuel_type": "PE",
      "total_tests": 1523,
      "total_passes": 717,
      "total_fails": 673,
      "pass_rate": 47.08,
      "avg_mileage": 69173.0,
      "avg_age_years": 12.5,
      "pass_rate_vs_national": -24.43
    },
    {
      "model": "AVEO",
      "model_year": 2009,
      "fuel_type": "PE",
      "total_tests": 3352,
      "total_passes": 1545,
      "total_fails": 1521,
      "pass_rate": 46.09,
      "avg_mileage": 70797.0,
      "avg_age_years": 13.5,
      "pass_rate_vs_national": -25.42
    },
    {
      "model": "LACETTI",
      "model_year": 2007,
      "fuel_type": "PE",
      "total_tests": 483,
      "total_passes": 222,
      "total_fails": 222,
      "pass_rate": 45.96,
      "avg_mileage": 77474.0,
      "avg_age_years": 15.5,
      "pass_rate_vs_national": -25.55
    },
    {
      "model": "AVEO",
      "model_year": 2008,
      "fuel_type": "PE",
      "total_tests": 891,
      "total_passes": 405,
      "total_fails": 397,
      "pass_rate": 45.45,
      "avg_mileage": 71807.0,
      "avg_age_years": 14.3,
      "pass_rate_vs_national": -26.06
    },
    {
      "model": "MATIZ",
      "model_year": 2005,
      "fuel_type": "PE",
      "total_tests": 733,
      "total_passes": 333,
      "total_fails": 343,
      "pass_rate": 45.43,
      "avg_mileage": 58528.0,
      "avg_age_years": 17.4,
      "pass_rate_vs_national": -26.08
    },
    {
      "model": "LACETTI",
      "model_year": 2005,
      "fuel_type": "PE",
      "total_tests": 198,
      "total_passes": 89,
      "total_fails": 96,
      "pass_rate": 44.95,
      "avg_mileage": 71116.0,
      "avg_age_years": 17.3,
      "pass_rate_vs_national": -26.56
    },
    {
      "model": "KALOS",
      "model_year": 2005,
      "fuel_type": "PE",
      "total_tests": 579,
      "total_passes": 246,
      "total_fails": 285,
      "pass_rate": 42.49,
      "avg_mileage": 69255.0,
      "avg_age_years": 17.4,
      "pass_rate_vs_national": -29.02
    },
    {
      "model": "LACETTI",
      "model_year": 2006,
      "fuel_type": "PE",
      "total_tests": 368,
      "total_passes": 148,
      "total_fails": 190,
      "pass_rate": 40.22,
      "avg_mileage": 75610.0,
      "avg_age_years": 16.5,
      "pass_rate_vs_national": -31.29
    }
  ],
  "age_adjusted": {
    "methodology": "Compares each model's pass rate against the national average for cars of the same age. A positive score means the model performs better than average for its age.",
    "best_models": [
      {
        "model": "TRAX",
        "model_year": 2014,
        "fuel_type": "PE",
        "total_tests": 349,
        "avg_vs_national": 0.37,
        "durability_trend": -3.9,
        "best_age_band": {
          "age_band": "7-8 years",
          "band_order": 2,
          "pass_rate": 80.0,
          "national_pass_rate": 77.24,
          "vs_national": 2.76,
          "total_tests": 135,
          "avg_mileage": 57849.0
        },
        "worst_age_band": {
          "age_band": "9-10 years",
          "band_order": 3,
          "pass_rate": 70.09,
          "national_pass_rate": 71.23,
          "vs_national": -1.14,
          "total_tests": 214,
          "avg_mileage": 68203.0
        }
      },
      {
        "model": "TRAX",
        "model_year": 2013,
        "fuel_type": "PE",
        "total_tests": 496,
        "avg_vs_national": -1.27,
        "durability_trend": 0,
        "best_age_band": {
          "age_band": "9-10 years",
          "band_order": 3,
          "pass_rate": 69.96,
          "national_pass_rate": 71.23,
          "vs_national": -1.27,
          "total_tests": 496,
          "avg_mileage": 68377.0
        },
        "worst_age_band": {
          "age_band": "9-10 years",
          "band_order": 3,
          "pass_rate": 69.96,
          "national_pass_rate": 71.23,
          "vs_national": -1.27,
          "total_tests": 496,
          "avg_mileage": 68377.0
        }
      },
      {
        "model": "CRUZE",
        "model_year": 2009,
        "fuel_type": "PE",
        "total_tests": 210,
        "avg_vs_national": -1.77,
        "durability_trend": 0,
        "best_age_band": {
          "age_band": "13+ years",
          "band_order": 5,
          "pass_rate": 58.1,
          "national_pass_rate": 59.87,
          "vs_national": -1.77,
          "total_tests": 210,
          "avg_mileage": 81470.0
        },
        "worst_age_band": {
          "age_band": "13+ years",
          "band_order": 5,
          "pass_rate": 58.1,
          "national_pass_rate": 59.87,
          "vs_national": -1.77,
          "total_tests": 210,
          "avg_mileage": 81470.0
        }
      },
      {
        "model": "TRAX",
        "model_year": 2014,
        "fuel_type": "DI",
        "total_tests": 158,
        "avg_vs_national": -2.62,
        "durability_trend": -0.62,
        "best_age_band": {
          "age_band": "7-8 years",
          "band_order": 2,
          "pass_rate": 75.0,
          "national_pass_rate": 77.24,
          "vs_national": -2.24,
          "total_tests": 60,
          "avg_mileage": 74398.0
        },
        "worst_age_band": {
          "age_band": "9-10 years",
          "band_order": 3,
          "pass_rate": 68.37,
          "national_pass_rate": 71.23,
          "vs_national": -2.86,
          "total_tests": 98,
          "avg_mileage": 81276.0
        }
      },
      {
        "model": "CAPTIVA",
        "model_year": 2014,
        "fuel_type": "DI",
        "total_tests": 177,
        "avg_vs_national": -2.84,
        "durability_trend": 4.11,
        "best_age_band": {
          "age_band": "9-10 years",
          "band_order": 3,
          "pass_rate": 69.53,
          "national_pass_rate": 71.23,
          "vs_national": -1.7,
          "total_tests": 128,
          "avg_mileage": 83787.0
        },
        "worst_age_band": {
          "age_band": "7-8 years",
          "band_order": 2,
          "pass_rate": 71.43,
          "national_pass_rate": 77.24,
          "vs_national": -5.81,
          "total_tests": 49,
          "avg_mileage": 76091.0
        }
      },
      {
        "model": "CRUZE",
        "model_year": 2011,
        "fuel_type": "PE",
        "total_tests": 1023,
        "avg_vs_national": -3.98,
        "durability_trend": 0,
        "best_age_band": {
          "age_band": "11-12 years",
          "band_order": 4,
          "pass_rate": 62.56,
          "national_pass_rate": 66.54,
          "vs_national": -3.98,
          "total_tests": 1023,
          "avg_mileage": 75961.0
        },
        "worst_age_band": {
          "age_band": "11-12 years",
          "band_order": 4,
          "pass_rate": 62.56,
          "national_pass_rate": 66.54,
          "vs_national": -3.98,
          "total_tests": 1023,
          "avg_mileage": 75961.0
        }
      },
      {
        "model": "ORLANDO",
        "model_year": 2011,
        "fuel_type": "PE",
        "total_tests": 744,
        "avg_vs_national": -5.25,
        "durability_trend": 0,
        "best_age_band": {
          "age_band": "11-12 years",
          "band_order": 4,
          "pass_rate": 61.29,
          "national_pass_rate": 66.54,
          "vs_national": -5.25,
          "total_tests": 744,
          "avg_mileage": 90093.0
        },
        "worst_age_band": {
          "age_band": "11-12 years",
          "band_order": 4,
          "pass_rate": 61.29,
          "national_pass_rate": 66.54,
          "vs_national": -5.25,
          "total_tests": 744,
          "avg_mileage": 90093.0
        }
      },
      {
        "model": "MATIZ",
        "model_year": 2009,
        "fuel_type": "PE",
        "total_tests": 3911,
        "avg_vs_national": -6.18,
        "durability_trend": 0,
        "best_age_band": {
          "age_band": "13+ years",
          "band_order": 5,
          "pass_rate": 53.69,
          "national_pass_rate": 59.87,
          "vs_national": -6.18,
          "total_tests": 3911,
          "avg_mileage": 51958.0
        },
        "worst_age_band": {
          "age_band": "13+ years",
          "band_order": 5,
          "pass_rate": 53.69,
          "national_pass_rate": 59.87,
          "vs_national": -6.18,
          "total_tests": 3911,
          "avg_mileage": 51958.0
        }
      },
      {
        "model": "SPARK",
        "model_year": 2010,
        "fuel_type": "PE",
        "total_tests": 3348,
        "avg_vs_national": -6.36,
        "durability_trend": 5.52,
        "best_age_band": {
          "age_band": "13+ years",
          "band_order": 5,
          "pass_rate": 56.66,
          "national_pass_rate": 59.87,
          "vs_national": -3.21,
          "total_tests": 1435,
          "avg_mileage": 71467.0
        },
        "worst_age_band": {
          "age_band": "11-12 years",
          "band_order": 4,
          "pass_rate": 57.81,
          "national_pass_rate": 66.54,
          "vs_national": -8.73,
          "total_tests": 1913,
          "avg_mileage": 66094.0
        }
      },
      {
        "model": "CRUZE",
        "model_year": 2012,
        "fuel_type": "PE",
        "total_tests": 1182,
        "avg_vs_national": -7.07,
        "durability_trend": 2.81,
        "best_age_band": {
          "age_band": "11-12 years",
          "band_order": 4,
          "pass_rate": 60.69,
          "national_pass_rate": 66.54,
          "vs_national": -5.85,
          "total_tests": 669,
          "avg_mileage": 74502.0
        },
        "worst_age_band": {
          "age_band": "9-10 years",
          "band_order": 3,
          "pass_rate": 62.57,
          "national_pass_rate": 71.23,
          "vs_national": -8.66,
          "total_tests": 513,
          "avg_mileage": 70940.0
        }
      },
      {
        "model": "CAPTIVA",
        "model_year": 2007,
        "fuel_type": "DI",
        "total_tests": 233,
        "avg_vs_national": -7.08,
        "durability_trend": 0,
        "best_age_band": {
          "age_band": "13+ years",
          "band_order": 5,
          "pass_rate": 52.79,
          "national_pass_rate": 59.87,
          "vs_national": -7.08,
          "total_tests": 233,
          "avg_mileage": 112556.0
        },
        "worst_age_band": {
          "age_band": "13+ years",
          "band_order": 5,
          "pass_rate": 52.79,
          "national_pass_rate": 59.87,
          "vs_national": -7.08,
          "total_tests": 233,
          "avg_mileage": 112556.0
        }
      },
      {
        "model": "AVEO",
        "model_year": 2014,
        "fuel_type": "PE",
        "total_tests": 114,
        "avg_vs_national": -7.15,
        "durability_trend": 4.81,
        "best_age_band": {
          "age_band": "9-10 years",
          "band_order": 3,
          "pass_rate": 66.15,
          "national_pass_rate": 71.23,
          "vs_national": -5.08,
          "total_tests": 65,
          "avg_mileage": 54342.0
        },
        "worst_age_band": {
          "age_band": "7-8 years",
          "band_order": 2,
          "pass_rate": 67.35,
          "national_pass_rate": 77.24,
          "vs_national": -9.89,
          "total_tests": 49,
          "avg_mileage": 52227.0
        }
      },
      {
        "model": "ORLANDO",
        "model_year": 2014,
        "fuel_type": "DI",
        "total_tests": 158,
        "avg_vs_national": -7.54,
        "durability_trend": 5.63,
        "best_age_band": {
          "age_band": "9-10 years",
          "band_order": 3,
          "pass_rate": 65.69,
          "national_pass_rate": 71.23,
          "vs_national": -5.54,
          "total_tests": 102,
          "avg_mileage": 94661.0
        },
        "worst_age_band": {
          "age_band": "7-8 years",
          "band_order": 2,
          "pass_rate": 66.07,
          "national_pass_rate": 77.24,
          "vs_national": -11.17,
          "total_tests": 56,
          "avg_mileage": 84751.0
        }
      },
      {
        "model": "MATIZ",
        "model_year": 2008,
        "fuel_type": "PE",
        "total_tests": 2534,
        "avg_vs_national": -7.66,
        "durability_trend": 0,
        "best_age_band": {
          "age_band": "13+ years",
          "band_order": 5,
          "pass_rate": 52.21,
          "national_pass_rate": 59.87,
          "vs_national": -7.66,
          "total_tests": 2534,
          "avg_mileage": 56326.0
        },
        "worst_age_band": {
          "age_band": "13+ years",
          "band_order": 5,
          "pass_rate": 52.21,
          "national_pass_rate": 59.87,
          "vs_national": -7.66,
          "total_tests": 2534,
          "avg_mileage": 56326.0
        }
      },
      {
        "model": "CRUZE",
        "model_year": 2010,
        "fuel_type": "PE",
        "total_tests": 508,
        "avg_vs_national": -8.16,
        "durability_trend": -1.47,
        "best_age_band": {
          "age_band": "11-12 years",
          "band_order": 4,
          "pass_rate": 58.93,
          "national_pass_rate": 66.54,
          "vs_national": -7.61,
          "total_tests": 319,
          "avg_mileage": 79328.0
        },
        "worst_age_band": {
          "age_band": "13+ years",
          "band_order": 5,
          "pass_rate": 50.79,
          "national_pass_rate": 59.87,
          "vs_national": -9.08,
          "total_tests": 189,
          "avg_mileage": 82762.0
        }
      }
    ],
    "worst_models": [
      {
        "model": "AVEO",
        "model_year": 2012,
        "fuel_type": "DI",
        "total_tests": 413,
        "avg_vs_national": -21.77,
        "durability_trend": 4.22,
        "best_age_band": {
          "age_band": "11-12 years",
          "band_order": 4,
          "pass_rate": 46.97,
          "national_pass_rate": 66.54,
          "vs_national": -19.57,
          "total_tests": 198,
          "avg_mileage": 86677.0
        },
        "worst_age_band": {
          "age_band": "9-10 years",
          "band_order": 3,
          "pass_rate": 47.44,
          "national_pass_rate": 71.23,
          "vs_national": -23.79,
          "total_tests": 215,
          "avg_mileage": 84871.0
        }
      },
      {
        "model": "AVEO",
        "model_year": 2013,
        "fuel_type": "DI",
        "total_tests": 259,
        "avg_vs_national": -20.65,
        "durability_trend": 0,
        "best_age_band": {
          "age_band": "9-10 years",
          "band_order": 3,
          "pass_rate": 50.58,
          "national_pass_rate": 71.23,
          "vs_national": -20.65,
          "total_tests": 259,
          "avg_mileage": 78778.0
        },
        "worst_age_band": {
          "age_band": "9-10 years",
          "band_order": 3,
          "pass_rate": 50.58,
          "national_pass_rate": 71.23,
          "vs_national": -20.65,
          "total_tests": 259,
          "avg_mileage": 78778.0
        }
      },
      {
        "model": "LACETTI",
        "model_year": 2006,
        "fuel_type": "PE",
        "total_tests": 368,
        "avg_vs_national": -19.65,
        "durability_trend": 0,
        "best_age_band": {
          "age_band": "13+ years",
          "band_order": 5,
          "pass_rate": 40.22,
          "national_pass_rate": 59.87,
          "vs_national": -19.65,
          "total_tests": 368,
          "avg_mileage": 75610.0
        },
        "worst_age_band": {
          "age_band": "13+ years",
          "band_order": 5,
          "pass_rate": 40.22,
          "national_pass_rate": 59.87,
          "vs_national": -19.65,
          "total_tests": 368,
          "avg_mileage": 75610.0
        }
      },
      {
        "model": "LACETTI",
        "model_year": 2011,
        "fuel_type": "PE",
        "total_tests": 120,
        "avg_vs_national": -18.21,
        "durability_trend": 0,
        "best_age_band": {
          "age_band": "11-12 years",
          "band_order": 4,
          "pass_rate": 48.33,
          "national_pass_rate": 66.54,
          "vs_national": -18.21,
          "total_tests": 120,
          "avg_mileage": 74406.0
        },
        "worst_age_band": {
          "age_band": "11-12 years",
          "band_order": 4,
          "pass_rate": 48.33,
          "national_pass_rate": 66.54,
          "vs_national": -18.21,
          "total_tests": 120,
          "avg_mileage": 74406.0
        }
      },
      {
        "model": "KALOS",
        "model_year": 2005,
        "fuel_type": "PE",
        "total_tests": 579,
        "avg_vs_national": -17.38,
        "durability_trend": 0,
        "best_age_band": {
          "age_band": "13+ years",
          "band_order": 5,
          "pass_rate": 42.49,
          "national_pass_rate": 59.87,
          "vs_national": -17.38,
          "total_tests": 579,
          "avg_mileage": 69255.0
        },
        "worst_age_band": {
          "age_band": "13+ years",
          "band_order": 5,
          "pass_rate": 42.49,
          "national_pass_rate": 59.87,
          "vs_national": -17.38,
          "total_tests": 579,
          "avg_mileage": 69255.0
        }
      },
      {
        "model": "CRUZE",
        "model_year": 2014,
        "fuel_type": "DI",
        "total_tests": 295,
        "avg_vs_national": -16.29,
        "durability_trend": 4.74,
        "best_age_band": {
          "age_band": "9-10 years",
          "band_order": 3,
          "pass_rate": 57.06,
          "national_pass_rate": 71.23,
          "vs_national": -14.17,
          "total_tests": 163,
          "avg_mileage": 86243.0
        },
        "worst_age_band": {
          "age_band": "7-8 years",
          "band_order": 2,
          "pass_rate": 58.33,
          "national_pass_rate": 77.24,
          "vs_national": -18.91,
          "total_tests": 132,
          "avg_mileage": 80843.0
        }
      },
      {
        "model": "SPARK",
        "model_year": 2013,
        "fuel_type": "PE",
        "total_tests": 3962,
        "avg_vs_national": -16.26,
        "durability_trend": 0,
        "best_age_band": {
          "age_band": "9-10 years",
          "band_order": 3,
          "pass_rate": 54.97,
          "national_pass_rate": 71.23,
          "vs_national": -16.26,
          "total_tests": 3962,
          "avg_mileage": 61793.0
        },
        "worst_age_band": {
          "age_band": "9-10 years",
          "band_order": 3,
          "pass_rate": 54.97,
          "national_pass_rate": 71.23,
          "vs_national": -16.26,
          "total_tests": 3962,
          "avg_mileage": 61793.0
        }
      },
      {
        "model": "AVEO",
        "model_year": 2010,
        "fuel_type": "PE",
        "total_tests": 1523,
        "avg_vs_national": -16.22,
        "durability_trend": 6.31,
        "best_age_band": {
          "age_band": "13+ years",
          "band_order": 5,
          "pass_rate": 46.89,
          "national_pass_rate": 59.87,
          "vs_national": -12.98,
          "total_tests": 740,
          "avg_mileage": 71248.0
        },
        "worst_age_band": {
          "age_band": "11-12 years",
          "band_order": 4,
          "pass_rate": 47.25,
          "national_pass_rate": 66.54,
          "vs_national": -19.29,
          "total_tests": 783,
          "avg_mileage": 67211.0
        }
      },
      {
        "model": "SPARK",
        "model_year": 2014,
        "fuel_type": "PE",
        "total_tests": 784,
        "avg_vs_national": -15.1,
        "durability_trend": -4.34,
        "best_age_band": {
          "age_band": "7-8 years",
          "band_order": 2,
          "pass_rate": 64.65,
          "national_pass_rate": 77.24,
          "vs_national": -12.59,
          "total_tests": 331,
          "avg_mileage": 45278.0
        },
        "worst_age_band": {
          "age_band": "9-10 years",
          "band_order": 3,
          "pass_rate": 54.3,
          "national_pass_rate": 71.23,
          "vs_national": -16.93,
          "total_tests": 453,
          "avg_mileage": 53685.0
        }
      },
      {
        "model": "LACETTI",
        "model_year": 2005,
        "fuel_type": "PE",
        "total_tests": 198,
        "avg_vs_national": -14.92,
        "durability_trend": 0,
        "best_age_band": {
          "age_band": "13+ years",
          "band_order": 5,
          "pass_rate": 44.95,
          "national_pass_rate": 59.87,
          "vs_national": -14.92,
          "total_tests": 198,
          "avg_mileage": 71116.0
        },
        "worst_age_band": {
          "age_band": "13+ years",
          "band_order": 5,
          "pass_rate": 44.95,
          "national_pass_rate": 59.87,
          "vs_national": -14.92,
          "total_tests": 198,
          "avg_mileage": 71116.0
        }
      }
    ]
  },
  "durability": {
    "methodology": {
      "description": "Evidence-tiered durability scoring based on proven long-term data",
      "proven_threshold": "11+ years of MOT data required for 'proven' durability claims",
      "early_caveat": "Vehicles under 7 years old have not yet proven long-term durability",
      "scoring": "Performance vs national average for vehicles of the same age"
    },
    "reliability_summary": {
      "tier_distribution": {
        "maturing": {
          "vehicles": 26,
          "tests": 16293
        },
        "proven": {
          "vehicles": 44,
          "tests": 46045
        }
      },
      "proven_vehicles_tested": 50,
      "proven_above_average_pct": 2.0,
      "proven_avg_vs_national": -8.16,
      "durability_rating": "Below Average",
      "methodology_note": "Rating based only on vehicles with 11+ years of MOT data"
    },
    "durability_champions": {
      "description": "Vehicles with PROVEN durability - 11+ years old and still performing above average",
      "evidence_quality": "high",
      "vehicles": [
        {
          "model": "CRUZE",
          "model_year": 2009,
          "fuel_type": "PE",
          "age_band": "13+ years",
          "age_band_order": 5,
          "total_tests": 210,
          "pass_rate": 58.1,
          "vs_national_at_age": 0.8,
          "national_avg_for_age": 57.3,
          "avg_mileage": 81470.0,
          "maturity_tier": "proven",
          "evidence_quality": "high"
        }
      ]
    },
    "models_to_avoid": {
      "description": "Vehicles with PROVEN poor durability - 11+ years old and performing below average",
      "evidence_quality": "high",
      "vehicles": [
        {
          "model": "LACETTI",
          "model_year": 2006,
          "fuel_type": "PE",
          "age_band": "13+ years",
          "age_band_order": 5,
          "total_tests": 368,
          "pass_rate": 40.22,
          "vs_national_at_age": -17.08,
          "national_avg_for_age": 57.3,
          "avg_mileage": 75610.0,
          "maturity_tier": "proven",
          "evidence_quality": "high",
          "concern": "Below average durability at 13+ years"
        },
        {
          "model": "AVEO",
          "model_year": 2012,
          "fuel_type": "DI",
          "age_band": "11-12 years",
          "age_band_order": 4,
          "total_tests": 198,
          "pass_rate": 46.97,
          "vs_national_at_age": -15.86,
          "national_avg_for_age": 62.83,
          "avg_mileage": 86677.0,
          "maturity_tier": "proven",
          "evidence_quality": "high",
          "concern": "Below average durability at 11-12 years"
        },
        {
          "model": "KALOS",
          "model_year": 2005,
          "fuel_type": "PE",
          "age_band": "13+ years",
          "age_band_order": 5,
          "total_tests": 579,
          "pass_rate": 42.49,
          "vs_national_at_age": -14.81,
          "national_avg_for_age": 57.3,
          "avg_mileage": 69255.0,
          "maturity_tier": "proven",
          "evidence_quality": "high",
          "concern": "Below average durability at 13+ years"
        },
        {
          "model": "LACETTI",
          "model_year": 2011,
          "fuel_type": "PE",
          "age_band": "11-12 years",
          "age_band_order": 4,
          "total_tests": 120,
          "pass_rate": 48.33,
          "vs_national_at_age": -14.5,
          "national_avg_for_age": 62.83,
          "avg_mileage": 74406.0,
          "maturity_tier": "proven",
          "evidence_quality": "high",
          "concern": "Below average durability at 11-12 years"
        },
        {
          "model": "CRUZE",
          "model_year": 2012,
          "fuel_type": "DI",
          "age_band": "11-12 years",
          "age_band_order": 4,
          "total_tests": 174,
          "pass_rate": 49.43,
          "vs_national_at_age": -13.4,
          "national_avg_for_age": 62.83,
          "avg_mileage": 100885.0,
          "maturity_tier": "proven",
          "evidence_quality": "high",
          "concern": "Below average durability at 11-12 years"
        },
        {
          "model": "LACETTI",
          "model_year": 2005,
          "fuel_type": "PE",
          "age_band": "13+ years",
          "age_band_order": 5,
          "total_tests": 198,
          "pass_rate": 44.95,
          "vs_national_at_age": -12.35,
          "national_avg_for_age": 57.3,
          "avg_mileage": 71116.0,
          "maturity_tier": "proven",
          "evidence_quality": "high",
          "concern": "Below average durability at 13+ years"
        },
        {
          "model": "MATIZ",
          "model_year": 2005,
          "fuel_type": "PE",
          "age_band": "13+ years",
          "age_band_order": 5,
          "total_tests": 733,
          "pass_rate": 45.43,
          "vs_national_at_age": -11.87,
          "national_avg_for_age": 57.3,
          "avg_mileage": 58528.0,
          "maturity_tier": "proven",
          "evidence_quality": "high",
          "concern": "Below average durability at 13+ years"
        },
        {
          "model": "AVEO",
          "model_year": 2008,
          "fuel_type": "PE",
          "age_band": "13+ years",
          "age_band_order": 5,
          "total_tests": 891,
          "pass_rate": 45.45,
          "vs_national_at_age": -11.85,
          "national_avg_for_age": 57.3,
          "avg_mileage": 71807.0,
          "maturity_tier": "proven",
          "evidence_quality": "high",
          "concern": "Below average durability at 13+ years"
        },
        {
          "model": "LACETTI",
          "model_year": 2007,
          "fuel_type": "PE",
          "age_band": "13+ years",
          "age_band_order": 5,
          "total_tests": 483,
          "pass_rate": 45.96,
          "vs_national_at_age": -11.34,
          "national_avg_for_age": 57.3,
          "avg_mileage": 77474.0,
          "maturity_tier": "proven",
          "evidence_quality": "high",
          "concern": "Below average durability at 13+ years"
        },
        {
          "model": "AVEO",
          "model_year": 2009,
          "fuel_type": "PE",
          "age_band": "13+ years",
          "age_band_order": 5,
          "total_tests": 3352,
          "pass_rate": 46.09,
          "vs_national_at_age": -11.21,
          "national_avg_for_age": 57.3,
          "avg_mileage": 70797.0,
          "maturity_tier": "proven",
          "evidence_quality": "high",
          "concern": "Below average durability at 13+ years"
        }
      ]
    },
    "early_performers": {
      "description": "Newer vehicles showing strong early results (3-6 years)",
      "evidence_quality": "limited",
      "caveat": "Durability NOT yet proven - these vehicles have not been tested at older ages",
      "vehicles": []
    },
    "model_trajectories": {
      "KALOS": {
        "core_model": "KALOS",
        "years_covered": [
          2005,
          2006,
          2007,
          2008
        ],
        "trajectory_by_age": {
          "13+ years": {
            "band_order": 5,
            "national_avg": 57.3,
            "model_years": [
              {
                "year": 2005,
                "pass_rate": 42.49,
                "vs_national": -14.81,
                "total_tests": 579,
                "avg_mileage": 69255.0
              },
              {
                "year": 2006,
                "pass_rate": 47.97,
                "vs_national": -9.33,
                "total_tests": 688,
                "avg_mileage": 68335.0
              },
              {
                "year": 2007,
                "pass_rate": 48.55,
                "vs_national": -8.75,
                "total_tests": 1106,
                "avg_mileage": 66720.0
              },
              {
                "year": 2008,
                "pass_rate": 48.35,
                "vs_national": -8.95,
                "total_tests": 819,
                "avg_mileage": 61942.0
              }
            ]
          }
        },
        "best_proven_year": {
          "year": 2007,
          "vs_national": -8.75,
          "age_band": "13+ years"
        },
        "worst_proven_year": {
          "year": 2005,
          "vs_national": -14.81,
          "age_band": "13+ years"
        },
        "has_proven_data": true
      },
      "MATIZ": {
        "core_model": "MATIZ",
        "years_covered": [
          2005,
          2006,
          2007,
          2008,
          2009,
          2010
        ],
        "trajectory_by_age": {
          "11-12 years": {
            "band_order": 4,
            "national_avg": 62.83,
            "model_years": [
              {
                "year": 2010,
                "pass_rate": 56.66,
                "vs_national": -6.17,
                "total_tests": 323,
                "avg_mileage": 49293.0
              }
            ]
          },
          "13+ years": {
            "band_order": 5,
            "national_avg": 57.3,
            "model_years": [
              {
                "year": 2005,
                "pass_rate": 45.43,
                "vs_national": -11.87,
                "total_tests": 733,
                "avg_mileage": 58528.0
              },
              {
                "year": 2006,
                "pass_rate": 48.46,
                "vs_national": -8.84,
                "total_tests": 1463,
                "avg_mileage": 57294.0
              },
              {
                "year": 2007,
                "pass_rate": 49.36,
                "vs_national": -7.94,
                "total_tests": 2431,
                "avg_mileage": 56714.0
              },
              {
                "year": 2008,
                "pass_rate": 52.21,
                "vs_national": -5.09,
                "total_tests": 2534,
                "avg_mileage": 56326.0
              },
              {
                "year": 2009,
                "pass_rate": 53.69,
                "vs_national": -3.61,
                "total_tests": 3911,
                "avg_mileage": 51958.0
              },
              {
                "year": 2010,
                "pass_rate": 51.67,
                "vs_national": -5.63,
                "total_tests": 658,
                "avg_mileage": 53403.0
              }
            ]
          }
        },
        "best_proven_year": {
          "year": 2009,
          "vs_national": -3.61,
          "age_band": "13+ years"
        },
        "worst_proven_year": {
          "year": 2005,
          "vs_national": -11.87,
          "age_band": "13+ years"
        },
        "has_proven_data": true
      },
      "ORLANDO": {
        "core_model": "ORLANDO",
        "years_covered": [
          2011,
          2012,
          2013
        ],
        "trajectory_by_age": {
          "9-10 years": {
            "band_order": 3,
            "national_avg": 68.24,
            "model_years": [
              {
                "year": 2012,
                "pass_rate": 58.71,
                "vs_national": -9.53,
                "total_tests": 804,
                "avg_mileage": 81154.0
              },
              {
                "year": 2013,
                "pass_rate": 59.4,
                "vs_national": -8.84,
                "total_tests": 835,
                "avg_mileage": 84654.0
              }
            ]
          },
          "11-12 years": {
            "band_order": 4,
            "national_avg": 62.83,
            "model_years": [
              {
                "year": 2011,
                "pass_rate": 59.25,
                "vs_national": -3.58,
                "total_tests": 1367,
                "avg_mileage": 96238.0
              },
              {
                "year": 2012,
                "pass_rate": 56.8,
                "vs_national": -6.03,
                "total_tests": 1148,
                "avg_mileage": 89960.0
              }
            ]
          }
        },
        "best_proven_year": {
          "year": 2011,
          "vs_national": -3.58,
          "age_band": "11-12 years"
        },
        "worst_proven_year": {
          "year": 2012,
          "vs_national": -6.03,
          "age_band": "11-12 years"
        },
        "has_proven_data": true
      },
      "AVEO": {
        "core_model": "AVEO",
        "years_covered": [
          2008,
          2009,
          2010,
          2011,
          2012,
          2013
        ],
        "trajectory_by_age": {
          "9-10 years": {
            "band_order": 3,
            "national_avg": 68.24,
            "model_years": [
              {
                "year": 2012,
                "pass_rate": 53.23,
                "vs_national": -15.01,
                "total_tests": 804,
                "avg_mileage": 73762.0
              },
              {
                "year": 2013,
                "pass_rate": 56.7,
                "vs_national": -11.54,
                "total_tests": 1358,
                "avg_mileage": 70680.0
              }
            ]
          },
          "11-12 years": {
            "band_order": 4,
            "national_avg": 62.83,
            "model_years": [
              {
                "year": 2010,
                "pass_rate": 47.25,
                "vs_national": -15.58,
                "total_tests": 783,
                "avg_mileage": 67211.0
              },
              {
                "year": 2011,
                "pass_rate": 51.65,
                "vs_national": -11.18,
                "total_tests": 1210,
                "avg_mileage": 63293.0
              },
              {
                "year": 2012,
                "pass_rate": 52.33,
                "vs_national": -10.5,
                "total_tests": 730,
                "avg_mileage": 77481.0
              }
            ]
          },
          "13+ years": {
            "band_order": 5,
            "national_avg": 57.3,
            "model_years": [
              {
                "year": 2008,
                "pass_rate": 45.45,
                "vs_national": -11.85,
                "total_tests": 891,
                "avg_mileage": 71807.0
              },
              {
                "year": 2009,
                "pass_rate": 46.09,
                "vs_national": -11.21,
                "total_tests": 3352,
                "avg_mileage": 70797.0
              },
              {
                "year": 2010,
                "pass_rate": 46.89,
                "vs_national": -10.41,
                "total_tests": 740,
                "avg_mileage": 71248.0
              }
            ]
          }
        },
        "best_proven_year": {
          "year": 2010,
          "vs_national": -10.41,
          "age_band": "13+ years"
        },
        "worst_proven_year": {
          "year": 2010,
          "vs_national": -15.58,
          "age_band": "11-12 years"
        },
        "has_proven_data": true
      },
      "CRUZE": {
        "core_model": "CRUZE",
        "years_covered": [
          2009,
          2010,
          2011,
          2012,
          2013,
          2014
        ],
        "trajectory_by_age": {
          "7-8 years": {
            "band_order": 2,
            "national_avg": 75.13,
            "model_years": [
              {
                "year": 2014,
                "pass_rate": 61.65,
                "vs_national": -13.48,
                "total_tests": 206,
                "avg_mileage": 72360.0
              }
            ]
          },
          "9-10 years": {
            "band_order": 3,
            "national_avg": 68.24,
            "model_years": [
              {
                "year": 2012,
                "pass_rate": 62.45,
                "vs_national": -5.79,
                "total_tests": 807,
                "avg_mileage": 82365.0
              },
              {
                "year": 2013,
                "pass_rate": 61.84,
                "vs_national": -6.4,
                "total_tests": 1347,
                "avg_mileage": 83960.0
              },
              {
                "year": 2014,
                "pass_rate": 58.67,
                "vs_national": -9.57,
                "total_tests": 300,
                "avg_mileage": 79321.0
              }
            ]
          },
          "11-12 years": {
            "band_order": 4,
            "national_avg": 62.83,
            "model_years": [
              {
                "year": 2010,
                "pass_rate": 56.11,
                "vs_national": -6.72,
                "total_tests": 417,
                "avg_mileage": 87494.0
              },
              {
                "year": 2011,
                "pass_rate": 62.56,
                "vs_national": -0.27,
                "total_tests": 1023,
                "avg_mileage": 75961.0
              },
              {
                "year": 2012,
                "pass_rate": 58.37,
                "vs_national": -4.46,
                "total_tests": 843,
                "avg_mileage": 87694.0
              }
            ]
          },
          "13+ years": {
            "band_order": 5,
            "national_avg": 57.3,
            "model_years": [
              {
                "year": 2009,
                "pass_rate": 58.1,
                "vs_national": 0.8,
                "total_tests": 210,
                "avg_mileage": 81470.0
              },
              {
                "year": 2010,
                "pass_rate": 52.67,
                "vs_national": -4.63,
                "total_tests": 300,
                "avg_mileage": 96597.0
              }
            ]
          }
        },
        "best_proven_year": {
          "year": 2009,
          "vs_national": 0.8,
          "age_band": "13+ years"
        },
        "worst_proven_year": {
          "year": 2010,
          "vs_national": -6.72,
          "age_band": "11-12 years"
        },
        "has_proven_data": true
      },
      "CAPTIVA": {
        "core_model": "CAPTIVA",
        "years_covered": [
          2007,
          2008,
          2009,
          2010,
          2011,
          2012,
          2013
        ],
        "trajectory_by_age": {
          "9-10 years": {
            "band_order": 3,
            "national_avg": 68.24,
            "model_years": [
              {
                "year": 2012,
                "pass_rate": 58.78,
                "vs_national": -9.46,
                "total_tests": 427,
                "avg_mileage": 86907.0
              },
              {
                "year": 2013,
                "pass_rate": 58.86,
                "vs_national": -9.38,
                "total_tests": 1055,
                "avg_mileage": 84637.0
              }
            ]
          },
          "11-12 years": {
            "band_order": 4,
            "national_avg": 62.83,
            "model_years": [
              {
                "year": 2010,
                "pass_rate": 49.01,
                "vs_national": -13.82,
                "total_tests": 1061,
                "avg_mileage": 105082.0
              },
              {
                "year": 2011,
                "pass_rate": 53.55,
                "vs_national": -9.28,
                "total_tests": 1253,
                "avg_mileage": 97038.0
              },
              {
                "year": 2012,
                "pass_rate": 53.61,
                "vs_national": -9.22,
                "total_tests": 595,
                "avg_mileage": 91737.0
              }
            ]
          },
          "13+ years": {
            "band_order": 5,
            "national_avg": 57.3,
            "model_years": [
              {
                "year": 2007,
                "pass_rate": 52.79,
                "vs_national": -4.51,
                "total_tests": 233,
                "avg_mileage": 112556.0
              },
              {
                "year": 2008,
                "pass_rate": 50.41,
                "vs_national": -6.89,
                "total_tests": 734,
                "avg_mileage": 113866.0
              },
              {
                "year": 2009,
                "pass_rate": 49.24,
                "vs_national": -8.06,
                "total_tests": 788,
                "avg_mileage": 107389.0
              },
              {
                "year": 2010,
                "pass_rate": 50.2,
                "vs_national": -7.1,
                "total_tests": 755,
                "avg_mileage": 108464.0
              }
            ]
          }
        },
        "best_proven_year": {
          "year": 2007,
          "vs_national": -4.51,
          "age_band": "13+ years"
        },
        "worst_proven_year": {
          "year": 2010,
          "vs_national": -13.82,
          "age_band": "11-12 years"
        },
        "has_proven_data": true
      },
      "LACETTI": {
        "core_model": "LACETTI",
        "years_covered": [
          2006,
          2007,
          2008,
          2009
        ],
        "trajectory_by_age": {
          "13+ years": {
            "band_order": 5,
            "national_avg": 57.3,
            "model_years": [
              {
                "year": 2006,
                "pass_rate": 40.22,
                "vs_national": -17.08,
                "total_tests": 368,
                "avg_mileage": 75610.0
              },
              {
                "year": 2007,
                "pass_rate": 45.96,
                "vs_national": -11.34,
                "total_tests": 483,
                "avg_mileage": 77474.0
              },
              {
                "year": 2008,
                "pass_rate": 47.72,
                "vs_national": -9.58,
                "total_tests": 658,
                "avg_mileage": 74110.0
              },
              {
                "year": 2009,
                "pass_rate": 49.77,
                "vs_national": -7.53,
                "total_tests": 639,
                "avg_mileage": 75371.0
              }
            ]
          }
        },
        "best_proven_year": {
          "year": 2009,
          "vs_national": -7.53,
          "age_band": "13+ years"
        },
        "worst_proven_year": {
          "year": 2006,
          "vs_national": -17.08,
          "age_band": "13+ years"
        },
        "has_proven_data": true
      },
      "SPARK": {
        "core_model": "SPARK",
        "years_covered": [
          2010,
          2011,
          2012,
          2013,
          2014
        ],
        "trajectory_by_age": {
          "7-8 years": {
            "band_order": 2,
            "national_avg": 75.13,
            "model_years": [
              {
                "year": 2014,
                "pass_rate": 64.65,
                "vs_national": -10.48,
                "total_tests": 331,
                "avg_mileage": 45278.0
              }
            ]
          },
          "9-10 years": {
            "band_order": 3,
            "national_avg": 68.24,
            "model_years": [
              {
                "year": 2012,
                "pass_rate": 57.61,
                "vs_national": -10.63,
                "total_tests": 1642,
                "avg_mileage": 60961.0
              },
              {
                "year": 2013,
                "pass_rate": 54.97,
                "vs_national": -13.27,
                "total_tests": 3962,
                "avg_mileage": 61793.0
              },
              {
                "year": 2014,
                "pass_rate": 54.3,
                "vs_national": -13.94,
                "total_tests": 453,
                "avg_mileage": 53685.0
              }
            ]
          },
          "11-12 years": {
            "band_order": 4,
            "national_avg": 62.83,
            "model_years": [
              {
                "year": 2010,
                "pass_rate": 57.81,
                "vs_national": -5.02,
                "total_tests": 1913,
                "avg_mileage": 66094.0
              },
              {
                "year": 2011,
                "pass_rate": 54.55,
                "vs_national": -8.28,
                "total_tests": 3881,
                "avg_mileage": 67091.0
              },
              {
                "year": 2012,
                "pass_rate": 51.7,
                "vs_national": -11.13,
                "total_tests": 2143,
                "avg_mileage": 69226.0
              }
            ]
          },
          "13+ years": {
            "band_order": 5,
            "national_avg": 57.3,
            "model_years": [
              {
                "year": 2010,
                "pass_rate": 56.66,
                "vs_national": -0.64,
                "total_tests": 1435,
                "avg_mileage": 71467.0
              }
            ]
          }
        },
        "best_proven_year": {
          "year": 2010,
          "vs_national": -0.64,
          "age_band": "13+ years"
        },
        "worst_proven_year": {
          "year": 2012,
          "vs_national": -11.13,
          "age_band": "11-12 years"
        },
        "has_proven_data": true
      }
    }
  }
}